{"is_source_file": true, "format": "Java", "description": "This is the main application class for the Llama 3 Finetuning Backend, serving as the entry point and configuration class for the Spring Boot application. It enables async execution and scheduling, and sets up OpenAPI documentation information.", "external_files": ["org.springframework.boot.SpringApplication", "org.springframework.boot.autoconfigure.SpringBootApplication", "org.springframework.scheduling.annotation.EnableAsync", "org.springframework.scheduling.annotation.EnableScheduling", "io.swagger.v3.oas.annotations.OpenAPIDefinition", "io.swagger.v3.oas.annotations.info.Info"], "external_methods": ["SpringApplication.run"], "published": ["com.example.finetunellama3backend.FinetuneLlama3BackendApplication"], "classes": [{"name": "FinetuneLlama3BackendApplication", "description": "Main Spring Boot application class for the backend, configuring scheduling, async execution, and API documentation."}], "methods": [{"name": "main", "description": "The entry point method that starts the Spring Boot application."}], "calls": ["SpringApplication.run(FinetuneLlama3BackendApplication.class, args)"], "search-terms": ["Spring Boot", "main application class", "finetuning backend", "scheduling", "async", "OpenAPI", "com.example.finetunellama3backend"], "state": 2, "file_id": 6, "knowledge_revision": 13, "git_revision": "", "hash": "e87ef65b246edbcb8d553a13f89f7383", "format-version": 4, "code-base-name": "finetune_llama3_backend", "filename": "finetune_llama3_backend/src/main/java/com/example/finetunellama3backend/FinetuneLlama3BackendApplication.java", "revision_history": [{"13": ""}]}